[{"id": 452957509, "body": "$SPY $QQQ $AAPL $TSLA\n\nWell today was interesting lol \ud83d\ude06", "created_at": "2022-04-18T20:02:03Z", "user": {"id": 3578933, "username": "magic_tape", "name": "KTF", "avatar_url": "https://avatars.stocktwits.com/production/3578933/thumb-1642314691.png", "avatar_url_ssl": "https://avatars.stocktwits.com/production/3578933/thumb-1642314691.png", "join_date": "2020-06-08", "official": false, "identity": "User", "classification": [], "followers": 313, "following": 251, "ideas": 19472, "watchlist_stocks_count": 8, "like_count": 66730, "plus_tier": "", "premium_room": "", "trade_app": false, "portfolio_waitlist": true, "portfolio_status": "waitlist", "trade_status": null}, "source": {"id": 1149, "title": "StockTwits for iOS", "url": "http://www.stocktwits.com/mobile"}, "symbols": [{"id": 686, "symbol": "AAPL", "title": "Apple Inc.", "aliases": [], "is_following": false, "watchlist_count": 807448, "has_pricing": true}, {"id": 7271, "symbol": "SPY", "title": "SPDR S&P 500 ETF", "aliases": [], "is_following": false, "watchlist_count": 421976, "has_pricing": true}, {"id": 8660, "symbol": "TSLA", "title": "Tesla Inc", "aliases": [], "is_following": false, "watchlist_count": 802336, "has_pricing": true}, {"id": 9581, "symbol": "QQQ", "title": "INVESCO QQQ TRUST UNIT SER 1", "aliases": ["QQQQ"], "is_following": false, "watchlist_count": 133940, "has_pricing": true}], "likes": {"total": 7, "user_ids": [5610106, 6001061, 3501391, 1651138, 6237018, 3845208, 5958518]}, "mentioned_users": [], "entities": {"giphy": {"id": "VbnUQpnihPSIgIXuZv", "ratio": 0.8}, "sentiment": null}}, {"id": 452956885, "body": "$AAPL closing above 165!!! \nLETS SEE WHAT HAPPENS TOMORROW! \n \nFOLLOW \n&amp; LETS MAKE MONEY\ud83d\udcb0 \n$SPY $QQQ", "created_at": "2022-04-18T20:00:47Z", "user": {"id": 6531010, "username": "HelpTraders", "name": "Legends", "avatar_url": "https://avatars.stocktwits.com/production/6531010/thumb-1650230544.png", "avatar_url_ssl": "https://avatars.stocktwits.com/production/6531010/thumb-1650230544.png", "join_date": "2022-04-06", "official": false, "identity": "User", "classification": [], "followers": 51, "following": 4, "ideas": 289, "watchlist_stocks_count": 5, "like_count": 55, "plus_tier": "", "premium_room": "", "trade_app": false, "trade_status": null}, "source": {"id": 2269, "title": "StockTwits Web", "url": "https://stocktwits.com"}, "symbols": [{"id": 686, "symbol": "AAPL", "title": "Apple Inc.", "aliases": [], "is_following": false, "watchlist_count": 807479, "has_pricing": true}, {"id": 7271, "symbol": "SPY", "title": "SPDR S&P 500 ETF", "aliases": [], "is_following": false, "watchlist_count": 422026, "has_pricing": true}, {"id": 9581, "symbol": "QQQ", "title": "INVESCO QQQ TRUST UNIT SER 1", "aliases": ["QQQQ"], "is_following": false, "watchlist_count": 133952, "has_pricing": true}], "likes": {"total": 2, "user_ids": [3260048, 2255127]}, "mentioned_users": [], "entities": {"sentiment": {"basic": "Bullish"}}}, {"id": 452956451, "body": "$BABA Ahh those last 5 mins of the day :o) \n \n$aapl $bb $lyv", "created_at": "2022-04-18T19:59:45Z", "user": {"id": 543250, "username": "GoodNewsBull", "name": "Rob C", "avatar_url": "https://avatars.stocktwits.com/production/543250/thumb-1572205873.png", "avatar_url_ssl": "https://avatars.stocktwits.com/production/543250/thumb-1572205873.png", "join_date": "2015-07-01", "official": false, "identity": "User", "classification": [], "followers": 4489, "following": 357, "ideas": 206510, "watchlist_stocks_count": 27, "like_count": 47168, "plus_tier": "", "premium_room": "", "trade_app": false, "trade_status": null}, "source": {"id": 2269, "title": "StockTwits Web", "url": "https://stocktwits.com"}, "symbols": [{"id": 686, "symbol": "AAPL", "title": "Apple Inc.", "aliases": [], "is_following": false, "watchlist_count": 807419, "has_pricing": true}, {"id": 3379, "symbol": "BB", "title": "BlackBerry Ltd", "aliases": ["RIMM", "BBRY"], "is_following": false, "watchlist_count": 134563, "has_pricing": true}, {"id": 6224, "symbol": "LYV", "title": "Live Nation Entertainment, Inc.", "aliases": [], "is_following": false, "watchlist_count": 5021, "has_pricing": true}, {"id": 12100, "symbol": "BABA", "title": "Alibaba", "aliases": ["ALIBABA"], "is_following": false, "watchlist_count": 354269, "has_pricing": true}], "likes": {"total": 2, "user_ids": [6258777, 1038640]}, "mentioned_users": [], "entities": {"sentiment": null}}, {"id": 452956230, "body": "$AAPL  \nClose below 165 = BEARISH \nClose above 165 = BULLISH \n \nFOLLOW \n&amp; LETS MAKE MONEY\ud83d\udcb0 \n$SPY $QQQ", "created_at": "2022-04-18T19:59:09Z", "user": {"id": 6531010, "username": "HelpTraders", "name": "Legends", "avatar_url": "https://avatars.stocktwits.com/production/6531010/thumb-1650230544.png", "avatar_url_ssl": "https://avatars.stocktwits.com/production/6531010/thumb-1650230544.png", "join_date": "2022-04-06", "official": false, "identity": "User", "classification": [], "followers": 51, "following": 4, "ideas": 289, "watchlist_stocks_count": 5, "like_count": 55, "plus_tier": "", "premium_room": "", "trade_app": false, "trade_status": null}, "source": {"id": 2269, "title": "StockTwits Web", "url": "https://stocktwits.com"}, "symbols": [{"id": 686, "symbol": "AAPL", "title": "Apple Inc.", "aliases": [], "is_following": false, "watchlist_count": 807479, "has_pricing": true}, {"id": 7271, "symbol": "SPY", "title": "SPDR S&P 500 ETF", "aliases": [], "is_following": false, "watchlist_count": 422026, "has_pricing": true}, {"id": 9581, "symbol": "QQQ", "title": "INVESCO QQQ TRUST UNIT SER 1", "aliases": ["QQQQ"], "is_following": false, "watchlist_count": 133952, "has_pricing": true}], "conversation": {"parent_message_id": 452956230, "in_reply_to_message_id": null, "parent": true, "replies": 2}, "likes": {"total": 1, "user_ids": [3260048]}, "mentioned_users": [], "entities": {"sentiment": {"basic": "Bullish"}}}, {"id": 452955810, "body": "$AMD $AMZN $AAPL $QQQ", "created_at": "2022-04-18T19:57:58Z", "user": {"id": 1567686, "username": "JuSdOit", "name": "Ed Columbo", "avatar_url": "https://avatars.stocktwits.com/production/1567686/thumb-1534524968.png", "avatar_url_ssl": "https://avatars.stocktwits.com/production/1567686/thumb-1534524968.png", "join_date": "2018-08-06", "official": false, "identity": "User", "classification": [], "followers": 264, "following": 25, "ideas": 14347, "watchlist_stocks_count": 81, "like_count": 7811, "plus_tier": "", "premium_room": "", "trade_app": false, "trade_status": null}, "source": {"id": 2095, "title": "StockTwits For Android ", "url": "http://www.stocktwits.com/mobile"}, "symbols": [{"id": 686, "symbol": "AAPL", "title": "Apple Inc.", "aliases": [], "is_following": false, "watchlist_count": 807479, "has_pricing": true}, {"id": 864, "symbol": "AMZN", "title": "Amazon.com Inc.", "aliases": [], "is_following": false, "watchlist_count": 506542, "has_pricing": true}, {"id": 4331, "symbol": "AMD", "title": "Advanced Micro Devices Inc.", "aliases": [], "is_following": false, "watchlist_count": 412345, "has_pricing": true}, {"id": 9581, "symbol": "QQQ", "title": "INVESCO QQQ TRUST UNIT SER 1", "aliases": ["QQQQ"], "is_following": false, "watchlist_count": 133952, "has_pricing": true}], "reshare_message": {"reshared_count": 1, "reshared_deleted": false, "reshared_user_deleted": false, "parent_reshared_deleted": false, "message": {"id": 452930686, "body": "$SPY What everyone says when a trade is not going their way ? It&#39;s someone else&#39;s fault.\n\nWhat everyone should say when....", "created_at": "2022-04-18T18:38:05Z", "user": {"id": 1567686, "username": "JuSdOit", "name": "Ed Columbo", "avatar_url": "https://avatars.stocktwits.com/production/1567686/thumb-1534524968.png", "avatar_url_ssl": "https://avatars.stocktwits.com/production/1567686/thumb-1534524968.png", "join_date": "2018-08-06", "official": false, "identity": "User", "classification": [], "followers": 264, "following": 25, "ideas": 14347, "watchlist_stocks_count": 81, "like_count": 7811, "plus_tier": "", "premium_room": "", "trade_app": false, "trade_status": null}, "source": {"id": 2095, "title": "StockTwits For Android ", "url": "http://www.stocktwits.com/mobile"}, "symbols": [{"id": 7271, "symbol": "SPY", "title": "SPDR S&P 500 ETF", "aliases": [], "is_following": false, "watchlist_count": 422026, "has_pricing": true}], "likes": {"total": 2, "user_ids": [4269384, 641568]}, "mentioned_users": [], "entities": {"giphy": {"id": "3ohs7Ys9J8XyFVheg0", "ratio": 1.095890410958904}, "sentiment": null}}}, "mentioned_users": [], "entities": {"sentiment": null}}, {"id": 452954625, "body": "These charts are going to close interesting: \n$TSLA  \n$AAPL  \n$NVDA", "created_at": "2022-04-18T19:54:46Z", "user": {"id": 6531010, "username": "HelpTraders", "name": "Legends", "avatar_url": "https://avatars.stocktwits.com/production/6531010/thumb-1650230544.png", "avatar_url_ssl": "https://avatars.stocktwits.com/production/6531010/thumb-1650230544.png", "join_date": "2022-04-06", "official": false, "identity": "User", "classification": [], "followers": 51, "following": 4, "ideas": 289, "watchlist_stocks_count": 5, "like_count": 55, "plus_tier": "", "premium_room": "", "trade_app": false, "trade_status": null}, "source": {"id": 2269, "title": "StockTwits Web", "url": "https://stocktwits.com"}, "symbols": [{"id": 686, "symbol": "AAPL", "title": "Apple Inc.", "aliases": [], "is_following": false, "watchlist_count": 807310, "has_pricing": true}, {"id": 2925, "symbol": "NVDA", "title": "NVIDIA Corporation", "aliases": [], "is_following": false, "watchlist_count": 367450, "has_pricing": true}, {"id": 8660, "symbol": "TSLA", "title": "Tesla Inc", "aliases": [], "is_following": false, "watchlist_count": 802157, "has_pricing": true}], "conversation": {"parent_message_id": 452954625, "in_reply_to_message_id": null, "parent": true, "replies": 2}, "likes": {"total": 1, "user_ids": [5400587]}, "mentioned_users": [], "entities": {"sentiment": {"basic": "Bearish"}}}, {"id": 452954601, "body": "$AAPL Should reach 93.xx PSX,", "created_at": "2022-04-18T19:54:42Z", "user": {"id": 71094, "username": "BrianZ", "name": "brian", "avatar_url": "https://avatars.stocktwits.com/production/71094/thumb-1375317975.png", "avatar_url_ssl": "https://avatars.stocktwits.com/production/71094/thumb-1375317975.png", "join_date": "2011-04-13", "official": false, "identity": "User", "classification": [], "followers": 51, "following": 43, "ideas": 3958, "watchlist_stocks_count": 25, "like_count": 927, "plus_tier": "", "premium_room": "", "trade_app": false, "trade_status": null}, "source": {"id": 2269, "title": "StockTwits Web", "url": "https://stocktwits.com"}, "symbols": [{"id": 686, "symbol": "AAPL", "title": "Apple Inc.", "aliases": [], "is_following": false, "watchlist_count": 807348, "has_pricing": true}], "mentioned_users": [], "entities": {"sentiment": {"basic": "Bullish"}}}, {"id": 452953941, "body": "$AAPL \n\nOh well .. people are betting against this stock due to endless shilling and FUD ..\n\nGuess what .. no matter how you beat this stock down .. it will rise back up faster than you think.\n\nI\u2019m not worried because you keep sending endless FUD .. like recession and inflation..\n\nI call it bullshit .. they want part of 2.8 trillions money out .. but it\u2019s not stopping AAPL because it still make profit no matter how hard economic situation is.", "created_at": "2022-04-18T19:52:52Z", "user": {"id": 5928851, "username": "investclem1682", "name": "Clement So", "avatar_url": "https://avatars.stocktwits.com/production/5928851/thumb-1639363038.png", "avatar_url_ssl": "https://avatars.stocktwits.com/production/5928851/thumb-1639363038.png", "join_date": "2021-09-19", "official": false, "identity": "User", "classification": [], "followers": 23, "following": 5, "ideas": 2299, "watchlist_stocks_count": 28, "like_count": 1696, "plus_tier": "", "premium_room": "", "trade_app": false, "trade_status": null}, "source": {"id": 1149, "title": "StockTwits for iOS", "url": "http://www.stocktwits.com/mobile"}, "symbols": [{"id": 686, "symbol": "AAPL", "title": "Apple Inc.", "aliases": [], "is_following": false, "watchlist_count": 807348, "has_pricing": true}], "likes": {"total": 1, "user_ids": [2255127]}, "mentioned_users": [], "entities": {"sentiment": {"basic": "Bullish"}}}, {"id": 452953703, "body": "The fact is if you don\u2019t have a college degree and want 30$ per hour what do you think they will have to pay individuals who has a degree??? $100/hour. \nTo many hands out in this generation \n$AAPL $SPY $QQQ", "created_at": "2022-04-18T19:52:19Z", "user": {"id": 4416931, "username": "MEMEGANGHODL", "name": "APE SHIT", "avatar_url": "https://avatars.stocktwits.com/production/4416931/thumb-1641165085.png", "avatar_url_ssl": "https://avatars.stocktwits.com/production/4416931/thumb-1641165085.png", "join_date": "2020-12-11", "official": false, "identity": "User", "classification": [], "followers": 174, "following": 10, "ideas": 10068, "watchlist_stocks_count": 145, "like_count": 1268, "plus_tier": "month", "premium_room": "", "trade_app": false, "portfolio_waitlist": true, "portfolio_status": "waitlist", "trade_status": null}, "source": {"id": 1149, "title": "StockTwits for iOS", "url": "http://www.stocktwits.com/mobile"}, "symbols": [{"id": 686, "symbol": "AAPL", "title": "Apple Inc.", "aliases": [], "is_following": false, "watchlist_count": 807479, "has_pricing": true}, {"id": 7271, "symbol": "SPY", "title": "SPDR S&P 500 ETF", "aliases": [], "is_following": false, "watchlist_count": 422026, "has_pricing": true}, {"id": 9581, "symbol": "QQQ", "title": "INVESCO QQQ TRUST UNIT SER 1", "aliases": ["QQQQ"], "is_following": false, "watchlist_count": 133952, "has_pricing": true}], "conversation": {"parent_message_id": 452953703, "in_reply_to_message_id": null, "parent": true, "replies": 8}, "mentioned_users": [], "entities": {"sentiment": null}}, {"id": 452953601, "body": "$AAPL Just do it : HTBX", "created_at": "2022-04-18T19:52:02Z", "user": {"id": 3097964, "username": "paperblood", "name": "martin laplante", "avatar_url": "https://avatars.stocktwits.com/production/3097964/thumb-1582236667.png", "avatar_url_ssl": "https://avatars.stocktwits.com/production/3097964/thumb-1582236667.png", "join_date": "2020-02-15", "official": false, "identity": "User", "classification": [], "followers": 45, "following": 12, "ideas": 3203, "watchlist_stocks_count": 12, "like_count": 1095, "plus_tier": "", "premium_room": "", "trade_app": false, "trade_status": null}, "source": {"id": 2269, "title": "StockTwits Web", "url": "https://stocktwits.com"}, "symbols": [{"id": 686, "symbol": "AAPL", "title": "Apple Inc.", "aliases": [], "is_following": false, "watchlist_count": 807348, "has_pricing": true}], "mentioned_users": [], "entities": {"chart": {"thumb": "https://charts.stocktwits.com/production/small_452953601.gif", "large": "https://charts.stocktwits.com/production/large_452953601.gif", "original": "https://charts.stocktwits.com/production/original_452953601.gif", "url": "https://charts.stocktwits.com/production/original_452953601.gif"}, "sentiment": {"basic": "Bullish"}}}, {"id": 452953318, "body": "$AAPL  \nSwinging:  \n162.5p,  \nEx. EOW,  \nAvg 1.34 \n \nFOLLOW \n&amp; LETS MAKE MONEY\ud83d\udcb0 \n$SPY $QQQ", "created_at": "2022-04-18T19:51:20Z", "user": {"id": 6531010, "username": "HelpTraders", "name": "Legends", "avatar_url": "https://avatars.stocktwits.com/production/6531010/thumb-1650230544.png", "avatar_url_ssl": "https://avatars.stocktwits.com/production/6531010/thumb-1650230544.png", "join_date": "2022-04-06", "official": false, "identity": "User", "classification": [], "followers": 51, "following": 4, "ideas": 289, "watchlist_stocks_count": 5, "like_count": 55, "plus_tier": "", "premium_room": "", "trade_app": false, "trade_status": null}, "source": {"id": 2269, "title": "StockTwits Web", "url": "https://stocktwits.com"}, "symbols": [{"id": 686, "symbol": "AAPL", "title": "Apple Inc.", "aliases": [], "is_following": false, "watchlist_count": 807479, "has_pricing": true}, {"id": 7271, "symbol": "SPY", "title": "SPDR S&P 500 ETF", "aliases": [], "is_following": false, "watchlist_count": 422026, "has_pricing": true}, {"id": 9581, "symbol": "QQQ", "title": "INVESCO QQQ TRUST UNIT SER 1", "aliases": ["QQQQ"], "is_following": false, "watchlist_count": 133952, "has_pricing": true}], "conversation": {"parent_message_id": 452953318, "in_reply_to_message_id": null, "parent": true, "replies": 1}, "likes": {"total": 1, "user_ids": [6393638]}, "mentioned_users": [], "entities": {"sentiment": {"basic": "Bearish"}}}, {"id": 452953079, "body": "$SPY  $AAPL    \n \n  the $VIX is ONLY  at $22  days before Fed Chair Powell speaks on Thursday??   the rise in rates and selling Mortgage back securities (who will buy the the mortgage securities the FED sells?)  the  interest rates about to explode higher.. caution retail names.. caution everything imo..    \n \nexpect sharp spike in VIX as big money starts to add protection.. hardly anyone protected!", "created_at": "2022-04-18T19:50:48Z", "user": {"id": 509070, "username": "BotMuncher1", "name": "BOT MUNCHER", "avatar_url": "https://avatars.stocktwits.com/production/509070/thumb-1454365169.png", "avatar_url_ssl": "https://avatars.stocktwits.com/production/509070/thumb-1454365169.png", "join_date": "2015-04-28", "official": false, "identity": "User", "classification": [], "followers": 1675, "following": 0, "ideas": 13128, "watchlist_stocks_count": 0, "like_count": 3530, "plus_tier": "", "premium_room": "", "trade_app": false, "trade_status": null}, "source": {"id": 2269, "title": "StockTwits Web", "url": "https://stocktwits.com"}, "symbols": [{"id": 680, "symbol": "VIX", "title": "CBOE Volatility Index", "aliases": [], "is_following": false, "watchlist_count": 25955, "has_pricing": true}, {"id": 686, "symbol": "AAPL", "title": "Apple Inc.", "aliases": [], "is_following": false, "watchlist_count": 807470, "has_pricing": true}, {"id": 7271, "symbol": "SPY", "title": "SPDR S&P 500 ETF", "aliases": [], "is_following": false, "watchlist_count": 421997, "has_pricing": true}], "conversation": {"parent_message_id": 452953079, "in_reply_to_message_id": null, "parent": true, "replies": 1}, "likes": {"total": 1, "user_ids": [2219369]}, "mentioned_users": [], "entities": {"chart": {"thumb": "https://charts.stocktwits.com/production/small_452953079.png", "large": "https://charts.stocktwits.com/production/large_452953079.png", "original": "https://charts.stocktwits.com/production/original_452953079.png", "url": "https://charts.stocktwits.com/production/original_452953079.png"}, "sentiment": null}}, {"id": 452952998, "body": "$AAPL $TSLA $MSFT $NVDA $SPY \nSPY $340 next month \ud83d\ude4f", "created_at": "2022-04-18T19:50:35Z", "user": {"id": 1165200, "username": "Sherry___", "name": "Sherry, Not Shitty", "avatar_url": "https://avatars.stocktwits.com/production/1165200/thumb-1649386525.png", "avatar_url_ssl": "https://avatars.stocktwits.com/production/1165200/thumb-1649386525.png", "join_date": "2017-08-22", "official": false, "identity": "User", "classification": [], "followers": 5134, "following": 170, "ideas": 38333, "watchlist_stocks_count": 30, "like_count": 94027, "plus_tier": "", "premium_room": "", "trade_app": false, "trade_status": "PENDING_MFA"}, "source": {"id": 1149, "title": "StockTwits for iOS", "url": "http://www.stocktwits.com/mobile"}, "symbols": [{"id": 686, "symbol": "AAPL", "title": "Apple Inc.", "aliases": [], "is_following": false, "watchlist_count": 807310, "has_pricing": true}, {"id": 2735, "symbol": "MSFT", "title": "Microsoft Corporation", "aliases": [], "is_following": false, "watchlist_count": 392933, "has_pricing": true}, {"id": 2925, "symbol": "NVDA", "title": "NVIDIA Corporation", "aliases": [], "is_following": false, "watchlist_count": 367450, "has_pricing": true}, {"id": 7271, "symbol": "SPY", "title": "SPDR S&P 500 ETF", "aliases": [], "is_following": false, "watchlist_count": 421830, "has_pricing": true}, {"id": 8660, "symbol": "TSLA", "title": "Tesla Inc", "aliases": [], "is_following": false, "watchlist_count": 802157, "has_pricing": true}], "likes": {"total": 8, "user_ids": [1540915, 3578933, 1165200, 6356405, 6393638, 6204413, 5407724, 6374037]}, "mentioned_users": [], "entities": {"chart": {"thumb": "https://charts.stocktwits.com/production/small_452952998.gif", "large": "https://charts.stocktwits.com/production/large_452952998.gif", "original": "https://charts.stocktwits.com/production/original_452952998.gif", "url": "https://charts.stocktwits.com/production/original_452952998.gif"}, "sentiment": {"basic": "Bearish"}}}, {"id": 452952972, "body": "$AAPL \nAnyone wanting 30$ an hour just to work at a place with phones and computers that sell them selves is a moron. A greedy and unreasonable one. If your not a tech person in the back or security guard you don\u2019t deserve 30$/hour to stand on the floor greeting ppl \n$SPY $QQQ", "created_at": "2022-04-18T19:50:32Z", "user": {"id": 4416931, "username": "MEMEGANGHODL", "name": "APE SHIT", "avatar_url": "https://avatars.stocktwits.com/production/4416931/thumb-1641165085.png", "avatar_url_ssl": "https://avatars.stocktwits.com/production/4416931/thumb-1641165085.png", "join_date": "2020-12-11", "official": false, "identity": "User", "classification": [], "followers": 174, "following": 10, "ideas": 10068, "watchlist_stocks_count": 145, "like_count": 1268, "plus_tier": "month", "premium_room": "", "trade_app": false, "portfolio_waitlist": true, "portfolio_status": "waitlist", "trade_status": null}, "source": {"id": 1149, "title": "StockTwits for iOS", "url": "http://www.stocktwits.com/mobile"}, "symbols": [{"id": 686, "symbol": "AAPL", "title": "Apple Inc.", "aliases": [], "is_following": false, "watchlist_count": 807479, "has_pricing": true}, {"id": 7271, "symbol": "SPY", "title": "SPDR S&P 500 ETF", "aliases": [], "is_following": false, "watchlist_count": 422026, "has_pricing": true}, {"id": 9581, "symbol": "QQQ", "title": "INVESCO QQQ TRUST UNIT SER 1", "aliases": ["QQQQ"], "is_following": false, "watchlist_count": 133952, "has_pricing": true}], "likes": {"total": 2, "user_ids": [4185395, 4805442]}, "mentioned_users": [], "entities": {"chart": {"thumb": "https://charts.stocktwits.com/production/small_452952972.png", "large": "https://charts.stocktwits.com/production/large_452952972.png", "original": "https://charts.stocktwits.com/production/original_452952972.png", "url": "https://charts.stocktwits.com/production/original_452952972.png"}, "sentiment": null}}, {"id": 452952005, "body": "$AAPL What a bleeding pos this has become", "created_at": "2022-04-18T19:47:50Z", "user": {"id": 5289482, "username": "Yankees4027", "name": "marc vincent", "avatar_url": "http://avatars.stocktwits.com/images/default_avatar_thumb.jpg", "avatar_url_ssl": "https://s3.amazonaws.com/st-avatars/images/default_avatar_thumb.jpg", "join_date": "2021-03-26", "official": false, "identity": "User", "classification": [], "followers": 16, "following": 19, "ideas": 2532, "watchlist_stocks_count": 54, "like_count": 1698, "plus_tier": "", "premium_room": "", "trade_app": false, "trade_status": null}, "source": {"id": 1149, "title": "StockTwits for iOS", "url": "http://www.stocktwits.com/mobile"}, "symbols": [{"id": 686, "symbol": "AAPL", "title": "Apple Inc.", "aliases": [], "is_following": false, "watchlist_count": 807348, "has_pricing": true}], "conversation": {"parent_message_id": 452952005, "in_reply_to_message_id": null, "parent": true, "replies": 1}, "likes": {"total": 1, "user_ids": [6393638]}, "mentioned_users": [], "entities": {"sentiment": null}}, {"id": 452951842, "body": "$AAPL $MSFT $GOOG $GOOGL $INTC .,", "created_at": "2022-04-18T19:47:22Z", "user": {"id": 903618, "username": "Islanders71", "name": "the Hoff", "avatar_url": "https://avatars.stocktwits.com/production/903618/thumb-1643595208.png", "avatar_url_ssl": "https://avatars.stocktwits.com/production/903618/thumb-1643595208.png", "join_date": "2016-12-16", "official": false, "identity": "User", "classification": [], "followers": 1527, "following": 2710, "ideas": 51757, "watchlist_stocks_count": 15, "like_count": 201607, "plus_tier": "", "premium_room": "", "trade_app": false, "trade_status": null}, "source": {"id": 2269, "title": "StockTwits Web", "url": "https://stocktwits.com"}, "symbols": [{"id": 686, "symbol": "AAPL", "title": "Apple Inc.", "aliases": [], "is_following": false, "watchlist_count": 807457, "has_pricing": true}, {"id": 2044, "symbol": "GOOG", "title": "Alphabet Inc. Class C", "aliases": [], "is_following": false, "watchlist_count": 229874, "has_pricing": true}, {"id": 2310, "symbol": "INTC", "title": "Intel Corporation", "aliases": [], "is_following": false, "watchlist_count": 116898, "has_pricing": true}, {"id": 2735, "symbol": "MSFT", "title": "Microsoft Corporation", "aliases": [], "is_following": false, "watchlist_count": 393098, "has_pricing": true}, {"id": 11938, "symbol": "GOOGL", "title": "Alphabet Inc. Class A", "aliases": [], "is_following": false, "watchlist_count": 132696, "has_pricing": true}], "reshare_message": {"reshared_count": 8, "reshared_deleted": false, "reshared_user_deleted": false, "parent_reshared_deleted": false, "message": {"id": 452935344, "body": "$AABB don\u2019t let the low T bears control the narrative. https://www.reddit.com/r/aabbstock/comments/u3i3ge/aabb_share_price_calculator/?utm_source=share&amp;utm_medium=ios_app&amp;utm_name=iossmf", "created_at": "2022-04-18T18:54:50Z", "user": {"id": 6252918, "username": "GhostofShizz", "name": "Ape shit For ape", "avatar_url": "https://avatars.stocktwits.com/production/6252918/thumb-1650259789.png", "avatar_url_ssl": "https://avatars.stocktwits.com/production/6252918/thumb-1650259789.png", "join_date": "2022-01-14", "official": false, "identity": "User", "classification": [], "followers": 132, "following": 130, "ideas": 1419, "watchlist_stocks_count": 9, "like_count": 2561, "plus_tier": "", "premium_room": "", "trade_app": false, "trade_status": null}, "source": {"id": 1149, "title": "StockTwits for iOS", "url": "http://www.stocktwits.com/mobile"}, "symbols": [{"id": 16402, "symbol": "AABB", "title": "Asia Broadband Inc", "aliases": [], "is_following": false, "watchlist_count": 40380, "has_pricing": true}], "links": [{"title": "AABB Share Price Calculator", "url": "https://www.reddit.com/r/aabbstock/comments/u3i3ge/aabb_share_price_calculator/?utm_source=share&utm_medium=ios_app&utm_name=iossmf", "shortened_url": "https://www.reddit.com/r/aabbstock/comments/u3i3ge/aabb_share_price_calculator/?utm_source=share&utm_medium=ios_app&utm_name=iossmf", "shortened_expanded_url": "reddit.com/r/aabbstock/comm...", "description": "56 votes, 11 comments. 5.3k members in the aabbstock community. A place to openly discuss AABB stock.", "image": "https://external-preview.redd.it/nyg-dK7AJkwkiUdkHUXEr090_8crtRwjoq410edOKhM.jpg?auto=webp&s=4947fd5ac7547a5c6cca165d8d9b5f7c0537ecae", "created_at": "2022-04-18T18:54:52Z", "video_url": null, "source": {"name": "reddit", "website": "https://www.reddit.com/"}}], "likes": {"total": 21, "user_ids": [3264663, 3668552, 6396757, 5273573, 4960785, 3419409, 6180566, 4638724, 6189336, 3119054, 5051974, 185888, 5111634, 5444986, 396816, 4431356, 3823646, 6187638, 903618, 4420113, 4959916]}, "mentioned_users": [], "entities": {"sentiment": {"basic": "Bullish"}}}}, "mentioned_users": [], "entities": {"sentiment": {"basic": "Bullish"}}}, {"id": 452951568, "body": "$FB $MSFT $GOOG $AAPL $AMZN", "created_at": "2022-04-18T19:46:30Z", "user": {"id": 5198706, "username": "degish", "name": "Ralph Boner", "avatar_url": "https://avatars.stocktwits.com/production/5198706/thumb-1615076186.png", "avatar_url_ssl": "https://avatars.stocktwits.com/production/5198706/thumb-1615076186.png", "join_date": "2021-03-07", "official": false, "identity": "User", "classification": [], "followers": 7, "following": 12, "ideas": 1176, "watchlist_stocks_count": 7, "like_count": 465, "plus_tier": "", "premium_room": "", "trade_app": false, "portfolio_waitlist": true, "portfolio_status": "waitlist", "trade_status": null}, "source": {"id": 1149, "title": "StockTwits for iOS", "url": "http://www.stocktwits.com/mobile"}, "symbols": [{"id": 686, "symbol": "AAPL", "title": "Apple Inc.", "aliases": [], "is_following": false, "watchlist_count": 807419, "has_pricing": true}, {"id": 864, "symbol": "AMZN", "title": "Amazon.com Inc.", "aliases": [], "is_following": false, "watchlist_count": 506510, "has_pricing": true}, {"id": 2044, "symbol": "GOOG", "title": "Alphabet Inc. Class C", "aliases": [], "is_following": false, "watchlist_count": 229851, "has_pricing": true}, {"id": 2735, "symbol": "MSFT", "title": "Microsoft Corporation", "aliases": [], "is_following": false, "watchlist_count": 393071, "has_pricing": true}, {"id": 7871, "symbol": "FB", "title": "META PLATFORMS INC", "aliases": ["FBOOK", "MTVS"], "is_following": false, "watchlist_count": 460565, "has_pricing": true}], "likes": {"total": 1, "user_ids": [3577412]}, "mentioned_users": [], "entities": {"giphy": {"id": "APovFSQl7dSwGHLafn", "ratio": 0.375}, "sentiment": null}}, {"id": 452950576, "body": "$AAPL", "created_at": "2022-04-18T19:43:54Z", "user": {"id": 6342303, "username": "Gucciforever", "name": "Sun lover", "avatar_url": "https://avatars.stocktwits.com/production/6342303/thumb-1645359288.png", "avatar_url_ssl": "https://avatars.stocktwits.com/production/6342303/thumb-1645359288.png", "join_date": "2022-02-20", "official": false, "identity": "User", "classification": [], "followers": 10, "following": 12, "ideas": 1065, "watchlist_stocks_count": 4, "like_count": 2097, "plus_tier": "", "premium_room": "", "trade_app": false, "trade_status": null}, "source": {"id": 1149, "title": "StockTwits for iOS", "url": "http://www.stocktwits.com/mobile"}, "symbols": [{"id": 686, "symbol": "AAPL", "title": "Apple Inc.", "aliases": [], "is_following": false, "watchlist_count": 807348, "has_pricing": true}], "mentioned_users": [], "entities": {"sentiment": {"basic": "Bullish"}}}, {"id": 452950538, "body": "$AAPL  \ud83c\udf4f Hedge Fund Shills, nonstop posting.  Take a look around.", "created_at": "2022-04-18T19:43:49Z", "user": {"id": 819540, "username": "hoyasaxa1978", "name": "hoyasaxa1978", "avatar_url": "http://avatars.stocktwits.com/images/default_avatar_thumb.jpg", "avatar_url_ssl": "https://s3.amazonaws.com/st-avatars/images/default_avatar_thumb.jpg", "join_date": "2016-08-14", "official": false, "identity": "User", "classification": [], "followers": 359, "following": 6, "ideas": 28920, "watchlist_stocks_count": 58, "like_count": 46934, "plus_tier": "", "premium_room": "", "trade_app": false, "portfolio_waitlist": true, "portfolio_status": "waitlist", "trade_status": null}, "source": {"id": 1149, "title": "StockTwits for iOS", "url": "http://www.stocktwits.com/mobile"}, "symbols": [{"id": 686, "symbol": "AAPL", "title": "Apple Inc.", "aliases": [], "is_following": false, "watchlist_count": 807353, "has_pricing": true}], "likes": {"total": 1, "user_ids": [5928851]}, "mentioned_users": [], "entities": {"sentiment": {"basic": "Bullish"}}}, {"id": 452950032, "body": "$AAPL $SPY $QQQ", "created_at": "2022-04-18T19:42:36Z", "user": {"id": 3405114, "username": "Hugs4Pugs4Ever", "name": "Hug4Pugs4Ever", "avatar_url": "https://avatars.stocktwits.com/production/3405114/thumb-1625686844.png", "avatar_url_ssl": "https://avatars.stocktwits.com/production/3405114/thumb-1625686844.png", "join_date": "2020-05-05", "official": false, "identity": "User", "classification": ["verified"], "followers": 1194, "following": 10, "ideas": 6096, "watchlist_stocks_count": 4, "like_count": 857, "plus_tier": "", "premium_room": "BeatTheMarketPros", "trade_app": false, "portfolio": "public", "portfolio_status": "public", "trade_status": null}, "source": {"id": 2269, "title": "StockTwits Web", "url": "https://stocktwits.com"}, "symbols": [{"id": 686, "symbol": "AAPL", "title": "Apple Inc.", "aliases": [], "is_following": false, "watchlist_count": 807479, "has_pricing": true}, {"id": 7271, "symbol": "SPY", "title": "SPDR S&P 500 ETF", "aliases": [], "is_following": false, "watchlist_count": 422026, "has_pricing": true}, {"id": 9581, "symbol": "QQQ", "title": "INVESCO QQQ TRUST UNIT SER 1", "aliases": ["QQQQ"], "is_following": false, "watchlist_count": 133952, "has_pricing": true}], "likes": {"total": 1, "user_ids": [375219]}, "mentioned_users": [], "entities": {"chart": {"thumb": "https://charts.stocktwits.com/production/small_452950032.png", "large": "https://charts.stocktwits.com/production/large_452950032.png", "original": "https://charts.stocktwits.com/production/original_452950032.png", "url": "https://charts.stocktwits.com/production/original_452950032.png"}, "sentiment": null}}, {"id": 452949819, "body": "$AAPL Added a bit", "created_at": "2022-04-18T19:42:04Z", "user": {"id": 1869224, "username": "Looneyjoon", "name": "Joon", "avatar_url": "https://avatars.stocktwits.com/production/1869224/thumb-1598042096.png", "avatar_url_ssl": "https://avatars.stocktwits.com/production/1869224/thumb-1598042096.png", "join_date": "2019-02-13", "official": false, "identity": "User", "classification": [], "followers": 214, "following": 84, "ideas": 3621, "watchlist_stocks_count": 32, "like_count": 20773, "plus_tier": "", "premium_room": "", "trade_app": false, "portfolio_waitlist": true, "portfolio_status": "waitlist", "trade_status": null}, "source": {"id": 2269, "title": "StockTwits Web", "url": "https://stocktwits.com"}, "symbols": [{"id": 686, "symbol": "AAPL", "title": "Apple Inc.", "aliases": [], "is_following": false, "watchlist_count": 807348, "has_pricing": true}], "likes": {"total": 1, "user_ids": [6147187]}, "mentioned_users": [], "entities": {"sentiment": {"basic": "Bullish"}}}, {"id": 452949646, "body": "$AAPL    \ud83c\udf4f Indices\u2026all Indices, moving in sync.", "created_at": "2022-04-18T19:41:38Z", "user": {"id": 819540, "username": "hoyasaxa1978", "name": "hoyasaxa1978", "avatar_url": "http://avatars.stocktwits.com/images/default_avatar_thumb.jpg", "avatar_url_ssl": "https://s3.amazonaws.com/st-avatars/images/default_avatar_thumb.jpg", "join_date": "2016-08-14", "official": false, "identity": "User", "classification": [], "followers": 359, "following": 6, "ideas": 28920, "watchlist_stocks_count": 58, "like_count": 46934, "plus_tier": "", "premium_room": "", "trade_app": false, "portfolio_waitlist": true, "portfolio_status": "waitlist", "trade_status": null}, "source": {"id": 1149, "title": "StockTwits for iOS", "url": "http://www.stocktwits.com/mobile"}, "symbols": [{"id": 686, "symbol": "AAPL", "title": "Apple Inc.", "aliases": [], "is_following": false, "watchlist_count": 807348, "has_pricing": true}], "conversation": {"parent_message_id": 452949646, "in_reply_to_message_id": null, "parent": true, "replies": 1}, "likes": {"total": 1, "user_ids": [5928851]}, "mentioned_users": [], "entities": {"chart": {"thumb": "https://charts.stocktwits.com/production/small_452949646.png", "large": "https://charts.stocktwits.com/production/large_452949646.png", "original": "https://charts.stocktwits.com/production/original_452949646.png", "url": "https://charts.stocktwits.com/production/original_452949646.png"}, "sentiment": null}}, {"id": 452949583, "body": "$AAPL 100k 170 calls bought today that expire this Friday.  What in the actual hell is going on. \ud83d\ude02\ud83d\ude02\ud83d\ude02\ud83d\ude02, what a joke this casino is.", "created_at": "2022-04-18T19:41:30Z", "user": {"id": 3768591, "username": "Kauai_Estate", "name": "Kauai_Estate", "avatar_url": "https://avatars.stocktwits.com/production/3768591/thumb-1611112374.png", "avatar_url_ssl": "https://avatars.stocktwits.com/production/3768591/thumb-1611112374.png", "join_date": "2020-07-10", "official": false, "identity": "User", "classification": [], "followers": 73, "following": 39, "ideas": 3754, "watchlist_stocks_count": 165, "like_count": 556, "plus_tier": "", "premium_room": "", "trade_app": false, "portfolio_waitlist": true, "portfolio_status": "waitlist", "trade_status": null}, "source": {"id": 1149, "title": "StockTwits for iOS", "url": "http://www.stocktwits.com/mobile"}, "symbols": [{"id": 686, "symbol": "AAPL", "title": "Apple Inc.", "aliases": [], "is_following": false, "watchlist_count": 807348, "has_pricing": true}], "likes": {"total": 2, "user_ids": [3578933, 6393638]}, "mentioned_users": [], "entities": {"sentiment": {"basic": "Bearish"}}}, {"id": 452949056, "body": "$AAPL Bloated pig. Might see $100 this year", "created_at": "2022-04-18T19:40:04Z", "user": {"id": 1751701, "username": "AehrHeadClown", "name": "AehrHead Clown", "avatar_url": "https://avatars.stocktwits.com/production/1751701/thumb-1622217820.png", "avatar_url_ssl": "https://avatars.stocktwits.com/production/1751701/thumb-1622217820.png", "join_date": "2018-12-07", "official": false, "identity": "User", "classification": ["verified"], "followers": 69, "following": 107, "ideas": 5685, "watchlist_stocks_count": 115, "like_count": 2701, "plus_tier": "", "premium_room": "", "trade_app": false, "portfolio": "public", "portfolio_status": "public", "trade_status": null}, "source": {"id": 2095, "title": "StockTwits For Android ", "url": "http://www.stocktwits.com/mobile"}, "symbols": [{"id": 686, "symbol": "AAPL", "title": "Apple Inc.", "aliases": [], "is_following": false, "watchlist_count": 807348, "has_pricing": true}], "mentioned_users": [], "entities": {"sentiment": null}}, {"id": 452948862, "body": "$SPY Black Tuesday tomorrow $QQQ $MSFT $AAPL", "created_at": "2022-04-18T19:39:30Z", "user": {"id": 3714615, "username": "tradernoob004", "name": "TraderNoob004", "avatar_url": "http://avatars.stocktwits.com/images/default_avatar_thumb.jpg", "avatar_url_ssl": "https://s3.amazonaws.com/st-avatars/images/default_avatar_thumb.jpg", "join_date": "2020-06-30", "official": false, "identity": "User", "classification": [], "followers": 38, "following": 6, "ideas": 3454, "watchlist_stocks_count": 55, "like_count": 9475, "plus_tier": "", "premium_room": "", "trade_app": false, "trade_status": null}, "source": {"id": 1149, "title": "StockTwits for iOS", "url": "http://www.stocktwits.com/mobile"}, "symbols": [{"id": 686, "symbol": "AAPL", "title": "Apple Inc.", "aliases": [], "is_following": false, "watchlist_count": 807448, "has_pricing": true}, {"id": 2735, "symbol": "MSFT", "title": "Microsoft Corporation", "aliases": [], "is_following": false, "watchlist_count": 393085, "has_pricing": true}, {"id": 7271, "symbol": "SPY", "title": "SPDR S&P 500 ETF", "aliases": [], "is_following": false, "watchlist_count": 421976, "has_pricing": true}, {"id": 9581, "symbol": "QQQ", "title": "INVESCO QQQ TRUST UNIT SER 1", "aliases": ["QQQQ"], "is_following": false, "watchlist_count": 133940, "has_pricing": true}], "likes": {"total": 2, "user_ids": [6393638, 1165200]}, "mentioned_users": [], "entities": {"sentiment": {"basic": "Bearish"}}}, {"id": 452948825, "body": "$AAPL Unions are evil to economy", "created_at": "2022-04-18T19:39:23Z", "user": {"id": 2204160, "username": "Dimi1978", "name": "Dimitri", "avatar_url": "https://avatars.stocktwits.com/production/2204160/thumb-1619441955.png", "avatar_url_ssl": "https://avatars.stocktwits.com/production/2204160/thumb-1619441955.png", "join_date": "2019-07-18", "official": false, "identity": "User", "classification": [], "followers": 4, "following": 2, "ideas": 623, "watchlist_stocks_count": 10, "like_count": 902, "plus_tier": "", "premium_room": "", "trade_app": false, "trade_status": null}, "source": {"id": 2269, "title": "StockTwits Web", "url": "https://stocktwits.com"}, "symbols": [{"id": 686, "symbol": "AAPL", "title": "Apple Inc.", "aliases": [], "is_following": false, "watchlist_count": 807348, "has_pricing": true}], "mentioned_users": [], "entities": {"sentiment": null}}, {"id": 452948701, "body": "$AAPL TIMBERRRRRRR!!!", "created_at": "2022-04-18T19:39:04Z", "user": {"id": 5150008, "username": "nuyorican9452", "name": "Carlos Rivera", "avatar_url": "http://avatars.stocktwits.com/images/default_avatar_thumb.jpg", "avatar_url_ssl": "https://s3.amazonaws.com/st-avatars/images/default_avatar_thumb.jpg", "join_date": "2021-02-26", "official": false, "identity": "User", "classification": [], "followers": 2, "following": 2, "ideas": 118, "watchlist_stocks_count": 5, "like_count": 4, "plus_tier": "", "premium_room": "", "trade_app": false, "trade_status": null}, "source": {"id": 1149, "title": "StockTwits for iOS", "url": "http://www.stocktwits.com/mobile"}, "symbols": [{"id": 686, "symbol": "AAPL", "title": "Apple Inc.", "aliases": [], "is_following": false, "watchlist_count": 807348, "has_pricing": true}], "likes": {"total": 1, "user_ids": [6393638]}, "mentioned_users": [], "entities": {"sentiment": {"basic": "Bearish"}}}, {"id": 452948638, "body": "$AAPL gay", "created_at": "2022-04-18T19:38:51Z", "user": {"id": 5679022, "username": "BFofBearsWife", "name": "Utsav Mehra", "avatar_url": "https://avatars.stocktwits.com/production/5679022/thumb-1625870382.png", "avatar_url_ssl": "https://avatars.stocktwits.com/production/5679022/thumb-1625870382.png", "join_date": "2021-07-06", "official": false, "identity": "User", "classification": ["verified"], "followers": 82, "following": 33, "ideas": 8749, "watchlist_stocks_count": 8, "like_count": 2973, "plus_tier": "", "premium_room": "", "trade_app": false, "portfolio": "public", "portfolio_status": "public", "trade_status": null}, "source": {"id": 1149, "title": "StockTwits for iOS", "url": "http://www.stocktwits.com/mobile"}, "symbols": [{"id": 686, "symbol": "AAPL", "title": "Apple Inc.", "aliases": [], "is_following": false, "watchlist_count": 807348, "has_pricing": true}], "owned_symbols": ["AAPL"], "mentioned_users": [], "entities": {"sentiment": null}}, {"id": 452948160, "body": "$TSLA $SPY $QQQ $AAPL \n\nThese 2022 bulls are weak", "created_at": "2022-04-18T19:37:27Z", "user": {"id": 3578933, "username": "magic_tape", "name": "KTF", "avatar_url": "https://avatars.stocktwits.com/production/3578933/thumb-1642314691.png", "avatar_url_ssl": "https://avatars.stocktwits.com/production/3578933/thumb-1642314691.png", "join_date": "2020-06-08", "official": false, "identity": "User", "classification": [], "followers": 313, "following": 251, "ideas": 19472, "watchlist_stocks_count": 8, "like_count": 66747, "plus_tier": "", "premium_room": "", "trade_app": false, "portfolio_waitlist": true, "portfolio_status": "waitlist", "trade_status": null}, "source": {"id": 1149, "title": "StockTwits for iOS", "url": "http://www.stocktwits.com/mobile"}, "symbols": [{"id": 686, "symbol": "AAPL", "title": "Apple Inc.", "aliases": [], "is_following": false, "watchlist_count": 807470, "has_pricing": true}, {"id": 7271, "symbol": "SPY", "title": "SPDR S&P 500 ETF", "aliases": [], "is_following": false, "watchlist_count": 421997, "has_pricing": true}, {"id": 8660, "symbol": "TSLA", "title": "Tesla Inc", "aliases": [], "is_following": false, "watchlist_count": 802353, "has_pricing": true}, {"id": 9581, "symbol": "QQQ", "title": "INVESCO QQQ TRUST UNIT SER 1", "aliases": ["QQQQ"], "is_following": false, "watchlist_count": 133945, "has_pricing": true}], "likes": {"total": 8, "user_ids": [2912464, 5297199, 6548355, 3764467, 1643252, 3963322, 6393638, 3264603]}, "mentioned_users": [], "entities": {"sentiment": {"basic": "Bearish"}}}, {"id": 452947466, "body": "$AAPL Union at Apple store. oh....thats so sad. America is going down and down.....", "created_at": "2022-04-18T19:35:18Z", "user": {"id": 2204160, "username": "Dimi1978", "name": "Dimitri", "avatar_url": "https://avatars.stocktwits.com/production/2204160/thumb-1619441955.png", "avatar_url_ssl": "https://avatars.stocktwits.com/production/2204160/thumb-1619441955.png", "join_date": "2019-07-18", "official": false, "identity": "User", "classification": [], "followers": 4, "following": 2, "ideas": 623, "watchlist_stocks_count": 10, "like_count": 902, "plus_tier": "", "premium_room": "", "trade_app": false, "trade_status": null}, "source": {"id": 2269, "title": "StockTwits Web", "url": "https://stocktwits.com"}, "symbols": [{"id": 686, "symbol": "AAPL", "title": "Apple Inc.", "aliases": [], "is_following": false, "watchlist_count": 807348, "has_pricing": true}], "likes": {"total": 1, "user_ids": [6393638]}, "mentioned_users": [], "entities": {"sentiment": null}}]