[{"id": 406856630, "text": "$AAPL \n\nNew upward momentum", "time": 1637202632.0, "crested_time": "2021-11-17T18:30:32Z", "sentiment": "Bullish"}, {"id": 406856427, "text": "$AAPL No mercy for shorts! Well deserved!", "time": 1637202615.0, "crested_time": "2021-11-17T18:30:15Z", "sentiment": ""}, {"id": 406856193, "text": "$AAPL is this a good time to take profits or is it going up?", "time": 1637202596.0, "crested_time": "2021-11-17T18:29:56Z", "sentiment": ""}, {"id": 406856019, "text": "$TGT huge FOMO at 255.00 break.   $AAPL. $FB. $TSLA", "time": 1637202580.0, "crested_time": "2021-11-17T18:29:40Z", "sentiment": "Bullish"}, {"id": 406855081, "text": "$AAPL Fox Business Anchor Liz Clayman Says Will Host Wedbush Analyst Dan Ives On Program At 3 p.m. EST To Discuss Electric Vehicles \n \n11/17/21, 11:48 AM \nNovember 17, 2021 11:48 AM ET (BZ Newswire) -- Analyst Color \n \n As @Rivian @LucidMotors retreat &amp; @Tesla jumps, 1 of Wall Street&#39;s top analysts, Dan Ives @Wedbush will make his latest calls on all, &amp; $GM: EV dark horse? + what&#39;s behind his $AAPL #iPhone holiday sales prediction. See u3pET @ClamanCountdown $RIVN $LCID @FoxBusiness \n \nCopyright \u00a9 2021 Benzinga (BZ Newswire, http://www.benzinga.com/licensing). Benzinga does not provide investmentadvice. All rights reserved. Write to editorial@benzinga.com with any questions about this content. Subscribe to Benzinga Pro (http://pro.benzinga.com).", "time": 1637202491.0, "crested_time": "2021-11-17T18:28:11Z", "sentiment": ""}, {"id": 406854464, "text": "$AAPL\n\nAdded 157.50 call nov 26", "time": 1637202433.0, "crested_time": "2021-11-17T18:27:13Z", "sentiment": "Bullish"}, {"id": 406854022, "text": "$AAPL closed my positions. Wait until Friday", "time": 1637202392.0, "crested_time": "2021-11-17T18:26:32Z", "sentiment": ""}, {"id": 406853754, "text": "$TTCF $AMC $AAPL $TSLA apes this stock is shorted very heavily by wall st and has already started squeezing today!!\ud83d\ude80\ud83d\udc8e\ud83d\ude4c\ud83c\udffb\ud83d\ude80\ud83d\ude80\ud83d\ude80\ud83c\udf1a", "time": 1637202367.0, "crested_time": "2021-11-17T18:26:07Z", "sentiment": "Bullish"}, {"id": 406853541, "text": "$DOGE.X $TSLA $BTC.X $AAPL $SPY", "time": 1637202347.0, "crested_time": "2021-11-17T18:25:47Z", "sentiment": "Bullish"}, {"id": 406853176, "text": "$AAPL $155 close would be amazing going to tomorrow", "time": 1637202313.0, "crested_time": "2021-11-17T18:25:13Z", "sentiment": "Bullish"}, {"id": 406853067, "text": "$AAPL Tap 155 and let\u2019s call it a day!!", "time": 1637202303.0, "crested_time": "2021-11-17T18:25:03Z", "sentiment": "Bullish"}, {"id": 406852852, "text": "$AAPL Supply chain easing?", "time": 1637202282.0, "crested_time": "2021-11-17T18:24:42Z", "sentiment": ""}, {"id": 406852794, "text": "$MRNA load all you can ASAP $PFE $SPY $TSLA $AAPL", "time": 1637202276.0, "crested_time": "2021-11-17T18:24:36Z", "sentiment": ""}, {"id": 406852495, "text": "I&#39;m buying $QQQ calls on all the dips. Easy 12% return in seconds. \n\nWe know this will bounce back in seconds. why miss the chance \n\nThere is no downside to $qqq \n\n$spy $aapl $tsla", "time": 1637202245.0, "crested_time": "2021-11-17T18:24:05Z", "sentiment": ""}, {"id": 406851868, "text": "$TSLA $AAPL $SPY  amost 52 week high. $TSLA will be there in a blink.  Bullish as f***", "time": 1637202191.0, "crested_time": "2021-11-17T18:23:11Z", "sentiment": "Bullish"}, {"id": 406851810, "text": "$MRNA massive gap fill to 277 and 336 that will fill soon\n\n$PFE $SPY $AAPL $TSLA", "time": 1637202186.0, "crested_time": "2021-11-17T18:23:06Z", "sentiment": "Bullish"}, {"id": 406851573, "text": "$AAPL chart looked too good", "time": 1637202165.0, "crested_time": "2021-11-17T18:22:45Z", "sentiment": "Bullish"}, {"id": 406850795, "text": "$AAPL \ud83d\udc40\ud83d\udc40\ud83d\udc40", "time": 1637202095.0, "crested_time": "2021-11-17T18:21:35Z", "sentiment": "Bullish"}, {"id": 406850704, "text": "$AAPL WHAT&#39;S THE CATALYST TODAY BRO?", "time": 1637202085.0, "crested_time": "2021-11-17T18:21:25Z", "sentiment": ""}, {"id": 406849576, "text": "$TRIT it\u2019s options week. If you don\u2019t know how to play this game yet and are scared by shorts driving the price down, then go trade $AAPL or $F", "time": 1637201979.0, "crested_time": "2021-11-17T18:19:39Z", "sentiment": ""}, {"id": 406848054, "text": "$AMZN $Tsla $Aapl $Bkng $Shop Opec week = premium haggle for the dealer", "time": 1637201837.0, "crested_time": "2021-11-17T18:17:17Z", "sentiment": ""}, {"id": 406846366, "text": "$AAPL I bought calls for 11/19 yall think I should roll them out for a farther time ? Not lookin to well \u2026 new to this option stuff I\u2019m more old fashioned share holder but Fucj it :/", "time": 1637201685.0, "crested_time": "2021-11-17T18:14:45Z", "sentiment": "Bullish"}, {"id": 406846341, "text": "$AAPL $GOOGL \u2764 Crytpocurrencies?? Missed on Bitcoin?? Got something much much bigger potentially. Keep ur\ud83d\udc41\ud83d\udc41\ud83d\udc41\ud83d\udc41\ud83d\udc41on this sleeping beast. \nIntroducing $AABBG.X $AABB \nA revolutionary Gold-Backed Crypto/TOKEN tied to .10 grams of Gold!!!!\nDownload AABBG APP Wallet from the Apple &amp; Google stores, follow setup instructions. Start investing today!!!!!\n\ud83d\udd25news out today... Tokens flying off the shelves even b4 the Exch is live... now, a  world first,  a FIAT-FREE Crytpocurrency Exchange will  be out anyday. DONT MISS IT!!\nhttps://finance.yahoo.com/news/asia-broadband-exceeds-1-1-154300335.html\nWww.aabbgoldtoken.com. \nWww.aabbexchange.com", "time": 1637201683.0, "crested_time": "2021-11-17T18:14:43Z", "sentiment": "Bullish"}, {"id": 406845416, "text": "$SPY Just has that Wall St Push up to Sell into feeling this week, have to really keep an eye on that.\n\nThey can be little devils sometimes :o)\n\n$aapl $amzn $rblx $RIVN", "time": 1637201597.0, "crested_time": "2021-11-17T18:13:17Z", "sentiment": ""}, {"id": 406844971, "text": "$MSFT $AAPL $BA $UNH 20 yr treasury auction\u2026 yields dipping\u2026curve will stay flattened is my bet", "time": 1637201555.0, "crested_time": "2021-11-17T18:12:35Z", "sentiment": "Bullish"}, {"id": 406844684, "text": "$AAPL I\u2019m up 135% from last year April\u2026not selling before 2050", "time": 1637201531.0, "crested_time": "2021-11-17T18:12:11Z", "sentiment": "Bullish"}, {"id": 406843355, "text": "$QQQ Dip bought $qqq calls when it was 0.01% down. Made a quick 6% profit within minutes. All dips will be bought in Nasdaq within seconds. \n\n$spy $aapl $tsla", "time": 1637201411.0, "crested_time": "2021-11-17T18:10:11Z", "sentiment": "Bullish"}, {"id": 406843203, "text": "$AAPL doesn\u2019t seem to having a ton of buying power left right now to push this to the next level", "time": 1637201398.0, "crested_time": "2021-11-17T18:09:58Z", "sentiment": ""}, {"id": 406843049, "text": "$AAPL That\u201ds it for today kids!!..", "time": 1637201384.0, "crested_time": "2021-11-17T18:09:44Z", "sentiment": "Bullish"}, {"id": 406842981, "text": "$AAPL It&#39;s obvious Berstein smokes crack. Wedbush analyst Dan Ives on Fox Business program today at 3pm EST. Watch it!", "time": 1637201377.0, "crested_time": "2021-11-17T18:09:37Z", "sentiment": "Bullish"}]