[{"id": 423633916, "text": "$AAPL back in at 178.09 even when I\u2019m wrong = I win on this stock \nis this stock the guy in the gym trying 2 bench press 6 plates but asks strangers for a spotter #HoldTheWeight", "time": 1641425502.0, "crested_time": "2022-01-05T15:31:42Z", "sentiment": "Bullish"}, {"id": 423633027, "text": "$AAPL     \ud83c\udf4f \u201cThat Short was \u201cnasty\u201d\u2026but, Bullish.", "time": 1641425417.0, "crested_time": "2022-01-05T15:30:17Z", "sentiment": ""}, {"id": 423632817, "text": "$AAPL Always buy the morning dip.", "time": 1641425400.0, "crested_time": "2022-01-05T15:30:00Z", "sentiment": ""}, {"id": 423632362, "text": "$aapl always buy the dip. $amzn always buy the daily chart low. $tsla always buy the halway pt dip coming no doubt \ud83d\ude0f. Earnings next month", "time": 1641425357.0, "crested_time": "2022-01-05T15:29:17Z", "sentiment": "Bullish"}, {"id": 423631137, "text": "$AAPL Running big MRVL \u2b06\ufe0f\u2b06\ufe0f", "time": 1641425236.0, "crested_time": "2022-01-05T15:27:16Z", "sentiment": ""}, {"id": 423630283, "text": "$AAPL a 2nd dip.....what to do with a dip?   LOL", "time": 1641425159.0, "crested_time": "2022-01-05T15:25:59Z", "sentiment": ""}, {"id": 423630197, "text": "$AAPL Giant W forming on the chart", "time": 1641425152.0, "crested_time": "2022-01-05T15:25:52Z", "sentiment": ""}, {"id": 423630067, "text": "$AAPL $F HERE COMES THE BOOM!", "time": 1641425139.0, "crested_time": "2022-01-05T15:25:39Z", "sentiment": "Bullish"}, {"id": 423629912, "text": "$AAPL did you see how much AAPL Bridgewater bought", "time": 1641425122.0, "crested_time": "2022-01-05T15:25:22Z", "sentiment": "Bearish"}, {"id": 423629080, "text": "$SPY $AAPL Today gives us another BTD opportunity. I am buying 2/4 SPY 480 C\u2019s and 1/21 AAPL 180 C\u2019s", "time": 1641425050.0, "crested_time": "2022-01-05T15:24:10Z", "sentiment": ""}, {"id": 423628955, "text": "$SNAP can this Cathie witch buy some $AAPL  I\u2019m trying to get in at a lower price \ud83d\ude02", "time": 1641425039.0, "crested_time": "2022-01-05T15:23:59Z", "sentiment": ""}, {"id": 423628175, "text": "$MSFT $SPY $AAPL $QQQ When bears keep reminding us of things we don\u2019t care about", "time": 1641424962.0, "crested_time": "2022-01-05T15:22:42Z", "sentiment": "Bullish"}, {"id": 423627708, "text": "$AAPL oversold on the 30M chart", "time": 1641424918.0, "crested_time": "2022-01-05T15:21:58Z", "sentiment": "Bullish"}, {"id": 423627534, "text": "$AAPL great buying opportunitiesopportunities $$$$$$\ud83c\udf4f\ud83c\udf4f\ud83c\udf4f\ud83c\udf4f\ud83c\udf4f\u2764\ufe0f\u2764\ufe0f\u2764\ufe0f\ud83c\udf4f\ud83c\udf4f\ud83c\udf4f", "time": 1641424902.0, "crested_time": "2022-01-05T15:21:42Z", "sentiment": "Bullish"}, {"id": 423626978, "text": "$AAPL        \ud83c\udf4f Massive Short.  No way to defend.  Patience.", "time": 1641424850.0, "crested_time": "2022-01-05T15:20:50Z", "sentiment": ""}, {"id": 423626747, "text": "$AAPL wheres the idiot who added $190s with \u201csmart money\u201d ?", "time": 1641424829.0, "crested_time": "2022-01-05T15:20:29Z", "sentiment": ""}, {"id": 423626727, "text": "$SPY $QQQ $AAPL \ud83d\udea8\ud83d\udea8POWELL TALKING  AT 1200 ET\ud83d\udea8\ud83d\udea8", "time": 1641424827.0, "crested_time": "2022-01-05T15:20:27Z", "sentiment": ""}, {"id": 423626481, "text": "$AAPL", "time": 1641424803.0, "crested_time": "2022-01-05T15:20:03Z", "sentiment": "Bullish"}, {"id": 423626320, "text": "$AAPL I see some big money added deep ITM calls....like 7+ per...and they are loading 10-50+ options....here she goes.", "time": 1641424789.0, "crested_time": "2022-01-05T15:19:49Z", "sentiment": "Bullish"}, {"id": 423626270, "text": "$AAPL $AMZN $AMD $QQQ $MSFT", "time": 1641424784.0, "crested_time": "2022-01-05T15:19:44Z", "sentiment": "Bullish"}, {"id": 423625888, "text": "$BABA baba is that rare case where growth, fundamental, and technicals all come together see zero reason not to load and hold and continue to accumulate. Have not see anything like this since $AAPL  lows", "time": 1641424751.0, "crested_time": "2022-01-05T15:19:11Z", "sentiment": "Bullish"}, {"id": 423625737, "text": "$AAPL making money :)", "time": 1641424738.0, "crested_time": "2022-01-05T15:18:58Z", "sentiment": "Bearish"}, {"id": 423625207, "text": "$GPRO can woodman finally let this go?   It\u2019s great that things are finally going I the right direction.  Maybe $aapl if time to scoop them up", "time": 1641424691.0, "crested_time": "2022-01-05T15:18:11Z", "sentiment": "Bullish"}, {"id": 423624764, "text": "$NVNXF $LLKKF $LCID $AAPL $DIS \u2708\ufe0f\u2708\ufe0f\u2708\ufe0f\u2708\ufe0f", "time": 1641424646.0, "crested_time": "2022-01-05T15:17:26Z", "sentiment": "Bullish"}, {"id": 423624752, "text": "$AAPL I don\u2019t see it but I have 18 days to be under 160 fingers crossed", "time": 1641424645.0, "crested_time": "2022-01-05T15:17:25Z", "sentiment": ""}, {"id": 423624692, "text": "@EDDOC $aapl always dumb money because it\u2019s so bullish.. the way this pool defies gravity is unreal", "time": 1641424638.0, "crested_time": "2022-01-05T15:17:18Z", "sentiment": "Bullish"}, {"id": 423624652, "text": "$AAPL $SPY   \ud83c\udf4f \ud83d\udc47Nonstop Shilling.  Gotta  Block.", "time": 1641424635.0, "crested_time": "2022-01-05T15:17:15Z", "sentiment": ""}, {"id": 423623534, "text": "$AAPL #easy Today  But #WhosKnow??? $SPY", "time": 1641424524.0, "crested_time": "2022-01-05T15:15:24Z", "sentiment": "Bearish"}, {"id": 423623169, "text": "$AAPL weaker than the nasdaq?? \n66 down vs 55 bps down. Cant be.", "time": 1641424488.0, "crested_time": "2022-01-05T15:14:48Z", "sentiment": ""}, {"id": 423623127, "text": "$ASML $AAPL \n\nBought some shares in combination with my already existed nok shares.", "time": 1641424484.0, "crested_time": "2022-01-05T15:14:44Z", "sentiment": ""}]